prometheus_distributed_client/__init__.py
prometheus_distributed_client/config.py
prometheus_distributed_client/redis.py
prometheus_distributed_client/sqlite.py
prometheus_distributed_client-2.1.3.dist-info/LICENSE
prometheus_distributed_client-2.1.3.dist-info/METADATA
prometheus_distributed_client-2.1.3.dist-info/WHEEL
prometheus_distributed_client-2.1.3.dist-info/RECORD
