Metadata-Version: 2.3
Name: prometheus-distributed-client
Version: 2.1.3
Summary: 
License: GPLv3
Requires-Python: >=3.9,<4.0
Classifier: License :: Other/Proprietary License
Classifier: Programming Language :: Python :: 3
Classifier: Programming Language :: Python :: 3.9
Classifier: Programming Language :: Python :: 3.10
Classifier: Programming Language :: Python :: 3.11
Classifier: Programming Language :: Python :: 3.12
Classifier: Programming Language :: Python :: 3.13
Requires-Dist: prometheus-client (==0.23.*)
Requires-Dist: redis (>=5)
